{
    "(0,0,0)": {
        "back": {
            "1": 428.75,
            "138": 520.0,
            "154": 520.0,
            "16": 517.5,
            "176": 525.0,
            "218": 516.25,
            "24": 525.0,
            "48": 525.0,
            "70": 508.0,
            "82": 516.6666870117188
        },
        "bottom": {
            "1": 402.5,
            "128": 510.0,
            "142": 508.3333435058594,
            "146": 510.0,
            "206": 490.0,
            "218": 505.0,
            "222": 515.0,
            "48": 50.0,
            "70": 507.0,
            "94": 515.0
        },
        "front": {
            "1": 420.5882263183594,
            "10": 500.8333435058594,
            "152": 515.0,
            "218": 505.0,
            "22": 500.0,
            "32": 520.0,
            "40": 515.0,
            "66": 500.0,
            "8": 515.0,
            "94": 505.0
        },
        "left": {
            "1": 425.0,
            "130": 505.0,
            "144": 515.0,
            "150": 500.0,
            "184": 515.0,
            "194": 500.0,
            "222": 491.0,
            "26": 510.0,
            "30": 510.0,
            "6": 503.3333435058594
        },
        "right": {
            "1": 409.80767822265625,
            "128": 470.0,
            "134": 465.0,
            "136": 463.3333435058594,
            "144": 462.0,
            "158": 467.5,
            "206": 470.0,
            "66": 470.0,
            "82": 470.0,
            "86": 465.0
        },
        "top": {
            "1": 417.0,
            "150": 492.5,
            "194": 500.0,
            "210": 498.0,
            "214": 500.0,
            "26": 507.5,
            "32": 500.0,
            "48": 505.0,
            "6": 495.0,
            "70": 505.0
        }
    },
    "(0,0,1)": {
        "back": {
            "1": 346.0,
            "136": 457.5,
            "146": 445.0,
            "152": 465.0,
            "154": 450.0,
            "198": 440.0,
            "214": 445.0,
            "26": 455.0,
            "32": 460.0,
            "82": 445.0
        },
        "bottom": {
            "1": 299.0909118652344,
            "136": 430.0,
            "144": 430.0,
            "152": 430.0,
            "168": 425.0,
            "194": 405.0,
            "214": 405.0,
            "26": 405.0,
            "56": 425.0,
            "90": 405.0
        },
        "front": {
            "1": 343.3333435058594,
            "128": 465.0,
            "130": 445.0,
            "14": 440.0,
            "210": 450.0,
            "22": 435.0,
            "30": 445.0,
            "66": 450.0,
            "90": 450.0,
            "94": 435.0
        },
        "left": {
            "1": 332.77777099609375,
            "154": 445.0,
            "184": 475.0,
            "210": 440.0,
            "214": 420.0,
            "40": 475.0,
            "56": 470.0,
            "74": 440.0,
            "82": 440.0,
            "86": 425.0
        },
        "right": {
            "1": 280.0,
            "130": 330.0,
            "14": 295.0,
            "152": 355.0,
            "168": 355.0,
            "210": 330.0,
            "66": 330.0,
            "70": 290.0,
            "74": 330.0,
            "82": 325.0
        },
        "top": {
            "1": 321.5,
            "142": 445.0,
            "168": 460.0,
            "194": 445.0,
            "214": 440.0,
            "32": 465.0,
            "56": 465.0,
            "6": 436.6666564941406,
            "66": 445.0,
            "70": 445.0
        }
    },
    "(0,0,2)": {
        "back": {
            "1": 425.0,
            "130": 505.0,
            "160": 525.0,
            "194": 515.0,
            "202": 515.0,
            "26": 515.0,
            "40": 525.0,
            "6": 510.0,
            "70": 515.0,
            "90": 520.0
        },
        "bottom": {
            "1": 435.71429443359375,
            "146": 520.0,
            "150": 515.0,
            "152": 525.0,
            "154": 525.0,
            "160": 520.0,
            "210": 520.0,
            "66": 520.0,
            "8": 520.0,
            "82": 520.0
        },
        "front": {
            "1": 435.0,
            "10": 520.0,
            "130": 510.0,
            "144": 520.0,
            "194": 515.0,
            "218": 515.0,
            "222": 515.0,
            "48": 520.0,
            "6": 515.0,
            "70": 520.0
        },
        "left": {
            "1": 433.75,
            "10": 515.0,
            "144": 510.0,
            "160": 515.0,
            "168": 515.0,
            "176": 510.0,
            "218": 515.0,
            "40": 515.0,
            "56": 515.0,
            "74": 515.0
        },
        "right": {
            "1": 410.0,
            "10": 470.0,
            "150": 470.0,
            "168": 485.0,
            "184": 475.0,
            "198": 465.0,
            "202": 470.0,
            "24": 480.0,
            "6": 470.0,
            "74": 470.0
        },
        "top": {
            "1": 433.4615478515625,
            "130": 502.5,
            "134": 500.0,
            "138": 505.0,
            "150": 505.0,
            "160": 510.0,
            "56": 515.0,
            "66": 510.0,
            "90": 505.0,
            "94": 507.5
        }
    },
    "(0,1,0)": {
        "back": {
            "1": 427.5,
            "138": 515.0,
            "142": 515.0,
            "176": 515.0,
            "184": 520.0,
            "48": 510.0,
            "56": 515.0,
            "70": 515.0,
            "78": 515.0,
            "90": 515.0
        },
        "bottom": {
            "1": 416.25,
            "138": 485.0,
            "144": 485.0,
            "176": 485.0,
            "198": 495.0,
            "26": 495.0,
            "32": 490.0,
            "56": 495.0,
            "86": 490.0,
            "94": 500.0
        },
        "front": {
            "1": 425.0,
            "134": 505.0,
            "154": 510.0,
            "158": 510.0,
            "184": 515.0,
            "26": 510.0,
            "30": 510.0,
            "40": 515.0,
            "74": 510.0,
            "90": 510.0
        },
        "left": {
            "1": 430.0,
            "14": 510.0,
            "144": 515.0,
            "184": 520.0,
            "198": 505.0,
            "222": 505.0,
            "26": 505.0,
            "40": 515.0,
            "56": 515.0,
            "74": 500.0
        },
        "right": {
            "1": 410.0,
            "158": 460.0,
            "168": 465.0,
            "194": 460.0,
            "202": 465.0,
            "222": 460.0,
            "26": 462.5,
            "30": 460.0,
            "56": 465.0,
            "78": 455.0
        },
        "top": {
            "1": 420.0,
            "134": 500.0,
            "152": 510.0,
            "160": 510.0,
            "168": 510.0,
            "18": 505.0,
            "206": 505.0,
            "22": 505.0,
            "24": 505.0,
            "70": 500.0
        }
    },
    "(0,1,1)": {
        "back": {
            "1": 356.6666564941406,
            "128": 480.0,
            "202": 465.0,
            "206": 475.0,
            "24": 485.0,
            "30": 470.0,
            "6": 470.0,
            "8": 475.0,
            "82": 470.0,
            "94": 475.0
        },
        "bottom": {
            "1": 314.5833435058594,
            "10": 420.0,
            "128": 440.0,
            "144": 440.0,
            "184": 440.0,
            "214": 420.0,
            "22": 415.0,
            "32": 440.0,
            "56": 440.0,
            "94": 420.0
        },
        "front": {
            "1": 355.0,
            "128": 475.0,
            "14": 470.0,
            "144": 470.0,
            "154": 465.0,
            "176": 475.0,
            "184": 470.0,
            "214": 465.0,
            "56": 470.0,
            "86": 460.0
        },
        "left": {
            "1": 339.0,
            "130": 450.0,
            "138": 450.0,
            "14": 440.0,
            "198": 435.0,
            "22": 435.0,
            "74": 450.0,
            "82": 445.0,
            "86": 435.0,
            "90": 450.0
        },
        "right": {
            "1": 308.6111145019531,
            "128": 400.0,
            "130": 370.0,
            "136": 395.0,
            "154": 375.0,
            "168": 395.0,
            "202": 375.0,
            "30": 330.0,
            "48": 395.0,
            "6": 325.0
        },
        "top": {
            "1": 330.0,
            "130": 450.0,
            "16": 470.0,
            "194": 445.0,
            "202": 450.0,
            "218": 450.0,
            "22": 445.0,
            "32": 475.0,
            "82": 445.0,
            "90": 450.0
        }
    },
    "(0,1,2)": {
        "back": {
            "1": 435.0,
            "10": 520.0,
            "130": 515.0,
            "136": 525.0,
            "138": 515.0,
            "184": 525.0,
            "198": 510.0,
            "222": 520.0,
            "48": 520.0,
            "78": 520.0
        },
        "bottom": {
            "1": 422.0,
            "138": 500.0,
            "142": 505.0,
            "144": 500.0,
            "146": 495.0,
            "198": 500.0,
            "206": 505.0,
            "218": 505.0,
            "74": 505.0,
            "90": 505.0
        },
        "front": {
            "1": 426.5,
            "10": 510.0,
            "136": 515.0,
            "138": 510.0,
            "194": 505.0,
            "198": 505.0,
            "214": 505.0,
            "30": 510.0,
            "56": 510.0,
            "90": 510.0
        },
        "left": {
            "1": 431.6666564941406,
            "10": 510.0,
            "144": 510.0,
            "146": 505.0,
            "176": 510.0,
            "198": 510.0,
            "214": 510.0,
            "6": 505.0,
            "78": 510.0,
            "94": 510.0
        },
        "right": {
            "1": 410.0,
            "128": 476.6666564941406,
            "130": 465.0,
            "136": 475.0,
            "14": 475.0,
            "168": 475.0,
            "214": 470.0,
            "6": 465.0,
            "70": 470.0,
            "82": 467.5
        },
        "top": {
            "1": 450.5,
            "136": 540.0,
            "150": 525.0,
            "198": 525.0,
            "202": 530.0,
            "210": 527.5,
            "32": 540.0,
            "40": 540.0,
            "70": 525.0,
            "82": 530.0
        }
    },
    "(0,2,0)": {
        "back": {
            "1": 448.0,
            "138": 525.0,
            "160": 525.0,
            "18": 525.0,
            "218": 530.0,
            "26": 530.0,
            "40": 515.0,
            "70": 525.0,
            "90": 530.0,
            "94": 530.0
        },
        "bottom": {
            "1": 415.0,
            "146": 480.0,
            "152": 485.0,
            "158": 490.0,
            "168": 485.0,
            "30": 490.0,
            "6": 485.0,
            "86": 485.0,
            "90": 485.0,
            "94": 485.0
        },
        "front": {
            "1": 434.1666564941406,
            "128": 520.0,
            "130": 505.0,
            "138": 510.0,
            "14": 505.0,
            "154": 505.0,
            "176": 515.0,
            "206": 510.0,
            "30": 510.0,
            "40": 517.5
        },
        "left": {
            "1": 426.0,
            "128": 515.0,
            "130": 505.0,
            "144": 515.0,
            "16": 515.0,
            "206": 505.0,
            "24": 515.0,
            "40": 510.0,
            "56": 517.5,
            "8": 517.5
        },
        "right": {
            "1": 410.0,
            "14": 470.0,
            "160": 465.0,
            "18": 465.0,
            "198": 470.0,
            "202": 475.0,
            "32": 465.0,
            "70": 470.0,
            "78": 470.0,
            "94": 470.0
        },
        "top": {
            "1": 435.0,
            "136": 535.0,
            "146": 520.0,
            "18": 520.0,
            "210": 520.0,
            "22": 525.0,
            "24": 540.0,
            "74": 525.0,
            "8": 535.0,
            "90": 525.0
        }
    },
    "(0,2,1)": {
        "back": {
            "1": 431.6666564941406,
            "128": 510.0,
            "134": 510.0,
            "154": 510.0,
            "176": 510.0,
            "40": 510.0,
            "66": 505.0,
            "70": 510.0,
            "82": 505.0,
            "90": 505.0
        },
        "bottom": {
            "1": 317.77777099609375,
            "10": 412.5,
            "130": 407.5,
            "134": 395.0,
            "144": 425.0,
            "18": 410.0,
            "194": 410.0,
            "202": 410.0,
            "32": 430.0,
            "78": 400.0
        },
        "front": {
            "1": 430.0,
            "138": 505.0,
            "142": 505.0,
            "144": 505.0,
            "168": 510.0,
            "184": 515.0,
            "194": 500.0,
            "218": 505.0,
            "66": 505.0,
            "94": 515.0
        },
        "left": {
            "1": 435.0,
            "138": 510.0,
            "158": 510.0,
            "18": 505.0,
            "198": 510.0,
            "202": 515.0,
            "206": 515.0,
            "24": 510.0,
            "30": 515.0,
            "40": 510.0
        },
        "right": {
            "1": 390.625,
            "138": 495.0,
            "158": 495.0,
            "176": 495.0,
            "202": 495.0,
            "222": 495.0,
            "24": 495.0,
            "26": 492.5,
            "66": 490.0,
            "86": 495.0
        },
        "top": {
            "1": 415.625,
            "138": 510.0,
            "152": 520.0,
            "158": 495.0,
            "202": 510.0,
            "214": 495.0,
            "218": 515.0,
            "30": 500.0,
            "40": 520.0,
            "48": 520.0
        }
    },
    "(0,2,2)": {
        "back": {
            "1": 441.0,
            "142": 520.0,
            "144": 525.0,
            "160": 520.0,
            "214": 520.0,
            "26": 515.0,
            "40": 520.0,
            "66": 510.0,
            "70": 515.0,
            "82": 515.0
        },
        "bottom": {
            "1": 419.5833435058594,
            "128": 495.0,
            "154": 495.0,
            "158": 495.0,
            "210": 490.0,
            "222": 500.0,
            "48": 490.0,
            "66": 490.0,
            "70": 490.0,
            "94": 500.0
        },
        "front": {
            "1": 444.23077392578125,
            "130": 520.0,
            "136": 515.0,
            "146": 520.0,
            "218": 520.0,
            "48": 515.0,
            "6": 525.0,
            "66": 522.5,
            "74": 525.0,
            "94": 525.0
        },
        "left": {
            "136": 510.0,
            "152": 510.0,
            "160": 510.0,
            "184": 505.0,
            "198": 515.0,
            "202": 515.0,
            "210": 510.0,
            "6": 515.0,
            "74": 515.0,
            "8": 510.0
        },
        "right": {
            "1": 410.0,
            "130": 465.0,
            "138": 475.0,
            "142": 465.0,
            "18": 470.0,
            "214": 460.0,
            "22": 460.0,
            "222": 460.0,
            "32": 470.0,
            "78": 465.0
        },
        "top": {
            "1": 455.4545593261719,
            "10": 535.0,
            "138": 535.0,
            "150": 530.0,
            "154": 535.0,
            "206": 540.0,
            "22": 535.0,
            "26": 535.0,
            "32": 545.0,
            "56": 545.0
        }
    },
    "(1,0,0)": {
        "back": {
            "1": 430.0,
            "16": 520.0,
            "176": 520.0,
            "18": 515.0,
            "210": 515.0,
            "24": 520.0,
            "30": 515.0,
            "70": 515.0,
            "8": 520.0,
            "86": 510.0
        },
        "bottom": {
            "1": 440.0,
            "14": 525.0,
            "146": 520.0,
            "152": 515.0,
            "154": 525.0,
            "18": 520.0,
            "198": 515.0,
            "214": 515.0,
            "26": 525.0,
            "6": 520.0
        },
        "front": {
            "1": 420.0,
            "128": 515.0,
            "134": 505.0,
            "160": 515.0,
            "176": 510.0,
            "184": 515.0,
            "206": 510.0,
            "218": 510.0,
            "70": 505.0,
            "82": 500.0
        },
        "left": {
            "1": 412.69232177734375,
            "134": 480.0,
            "138": 480.0,
            "142": 480.0,
            "16": 490.0,
            "176": 485.0,
            "198": 480.0,
            "40": 490.0,
            "78": 485.0,
            "90": 480.0
        },
        "right": {
            "1": 416.6666564941406,
            "138": 485.0,
            "158": 480.0,
            "18": 480.0,
            "194": 480.0,
            "218": 482.5,
            "26": 485.0,
            "8": 485.0,
            "82": 480.0,
            "86": 480.0
        },
        "top": {
            "1": 411.6666564941406,
            "154": 500.0,
            "160": 505.0,
            "202": 500.0,
            "218": 500.0,
            "26": 500.0,
            "32": 505.0,
            "40": 505.0,
            "66": 500.0,
            "78": 495.0
        }
    },
    "(1,0,1)": {
        "back": {
            "1": 370.0,
            "128": 485.0,
            "146": 455.0,
            "154": 455.0,
            "16": 485.0,
            "160": 485.0,
            "202": 460.0,
            "214": 425.0,
            "22": 425.0,
            "78": 430.0
        },
        "bottom": {
            "1": 280.0,
            "142": 365.0,
            "152": 410.0,
            "158": 360.0,
            "194": 360.0,
            "218": 360.0,
            "22": 360.0,
            "24": 410.0,
            "26": 365.0,
            "74": 365.0
        },
        "front": {
            "1": 305.0,
            "16": 430.0,
            "176": 430.0,
            "194": 390.0,
            "22": 365.0,
            "222": 370.0,
            "48": 430.0,
            "6": 367.5,
            "66": 390.0,
            "94": 370.0
        },
        "left": {
            "1": 298.75,
            "130": 365.0,
            "134": 340.0,
            "144": 390.0,
            "146": 365.0,
            "150": 335.0,
            "154": 370.0,
            "222": 340.0,
            "26": 370.0,
            "32": 395.0
        },
        "right": {
            "1": 300.0,
            "10": 370.0,
            "206": 345.0,
            "218": 372.5,
            "30": 345.0,
            "40": 395.0,
            "48": 397.5,
            "78": 345.0,
            "8": 390.0,
            "86": 345.0
        },
        "top": {
            "1": 585.0,
            "10": 555.0,
            "136": 565.0,
            "142": 530.0,
            "16": 565.0,
            "184": 565.0,
            "214": 530.0,
            "22": 530.0,
            "24": 565.0,
            "56": 565.0
        }
    },
    "(1,0,2)": {
        "back": {
            "1": 429.5454406738281,
            "136": 525.0,
            "142": 520.0,
            "158": 520.0,
            "168": 530.0,
            "214": 515.0,
            "222": 515.0,
            "66": 510.0,
            "86": 515.0,
            "94": 520.0
        },
        "bottom": {
            "1": 437.69232177734375,
            "14": 525.0,
            "158": 525.0,
            "16": 522.5,
            "18": 515.0,
            "184": 525.0,
            "194": 520.0,
            "26": 525.0,
            "90": 525.0,
            "94": 525.0
        },
        "front": {
            "1": 435.0,
            "128": 525.0,
            "138": 520.0,
            "184": 525.0,
            "218": 515.0,
            "26": 520.0,
            "56": 525.0,
            "6": 515.0,
            "70": 510.0,
            "94": 515.0
        },
        "left": {
            "1": 414.1666564941406,
            "128": 480.0,
            "130": 475.0,
            "136": 480.0,
            "14": 470.0,
            "146": 475.0,
            "150": 475.0,
            "26": 480.0,
            "78": 480.0,
            "86": 470.0
        },
        "right": {
            "1": 420.0,
            "144": 500.0,
            "160": 495.0,
            "176": 500.0,
            "184": 500.0,
            "210": 485.0,
            "30": 485.0,
            "6": 480.0,
            "74": 490.0,
            "90": 490.0
        },
        "top": {
            "1": 422.5,
            "10": 505.0,
            "134": 490.0,
            "152": 510.0,
            "40": 515.0,
            "6": 490.0,
            "78": 500.0,
            "82": 495.0,
            "86": 495.0,
            "94": 500.0
        }
    },
    "(1,1,0)": {
        "back": {
            "1": 424.28570556640625,
            "134": 505.0,
            "138": 510.0,
            "14": 510.0,
            "150": 500.0,
            "152": 525.0,
            "158": 510.0,
            "168": 515.0,
            "30": 510.0,
            "66": 510.0
        },
        "bottom": {
            "1": 410.0,
            "10": 490.0,
            "154": 490.0,
            "168": 490.0,
            "18": 485.0,
            "198": 490.0,
            "210": 480.0,
            "26": 490.0,
            "30": 495.0,
            "74": 485.0
        },
        "front": {
            "1": 441.25,
            "150": 515.0,
            "168": 535.0,
            "184": 535.0,
            "194": 520.0,
            "32": 530.0,
            "48": 525.0,
            "56": 530.0,
            "8": 530.0,
            "94": 525.0
        },
        "left": {
            "1": 418.8888854980469,
            "136": 495.0,
            "176": 492.5,
            "202": 490.0,
            "22": 490.0,
            "222": 490.0,
            "26": 495.0,
            "40": 490.0,
            "48": 495.0,
            "86": 485.0
        },
        "right": {
            "1": 420.0,
            "134": 480.0,
            "136": 485.0,
            "16": 480.0,
            "184": 490.0,
            "218": 485.0,
            "22": 475.0,
            "48": 480.0,
            "74": 480.0,
            "90": 480.0
        },
        "top": {
            "1": 410.0,
            "136": 510.0,
            "138": 497.5,
            "14": 505.0,
            "16": 505.0,
            "184": 510.0,
            "194": 495.0,
            "198": 495.0,
            "218": 500.0,
            "26": 505.0
        }
    },
    "(1,1,1)": {
        "back": {
            "1": 326.0,
            "138": 430.0,
            "144": 465.0,
            "146": 430.0,
            "16": 465.0,
            "18": 430.0,
            "22": 420.0,
            "40": 465.0,
            "66": 430.0,
            "86": 415.0
        },
        "bottom": {
            "1": 280.0,
            "134": 350.0,
            "138": 350.0,
            "146": 350.0,
            "158": 355.0,
            "160": 395.0,
            "40": 400.0,
            "70": 350.0,
            "8": 395.0,
            "90": 355.0
        },
        "front": {
            "1": 329.1666564941406,
            "142": 415.0,
            "146": 430.0,
            "154": 435.0,
            "184": 460.0,
            "210": 430.0,
            "40": 460.0,
            "56": 465.0,
            "86": 420.0,
            "90": 430.0
        },
        "left": {
            "1": 315.0,
            "136": 430.0,
            "144": 425.0,
            "168": 435.0,
            "198": 365.0,
            "202": 400.0,
            "6": 370.0,
            "66": 400.0,
            "70": 365.0,
            "90": 400.0
        },
        "right": {
            "1": 323.75,
            "134": 380.0,
            "138": 410.0,
            "16": 435.0,
            "194": 410.0,
            "218": 410.0,
            "24": 430.0,
            "26": 415.0,
            "30": 385.0,
            "32": 435.0
        },
        "top": {
            "1": 1165.0,
            "128": 865.0,
            "150": 830.0,
            "168": 870.0,
            "218": 855.0,
            "22": 830.0,
            "24": 865.0,
            "26": 855.0,
            "70": 830.0,
            "82": 840.0
        }
    },
    "(1,1,2)": {
        "back": {
            "1": 427.5,
            "130": 510.0,
            "138": 515.0,
            "198": 515.0,
            "218": 515.0,
            "222": 520.0,
            "26": 515.0,
            "30": 520.0,
            "66": 515.0,
            "8": 525.0
        },
        "bottom": {
            "1": 415.0,
            "128": 500.0,
            "134": 500.0,
            "14": 505.0,
            "142": 505.0,
            "176": 505.0,
            "198": 500.0,
            "210": 495.0,
            "214": 500.0,
            "78": 505.0
        },
        "front": {
            "1": 427.5,
            "14": 505.0,
            "150": 505.0,
            "158": 505.0,
            "206": 510.0,
            "6": 500.0,
            "74": 505.0,
            "8": 510.0,
            "82": 500.0,
            "86": 505.0
        },
        "left": {
            "1": 415.0,
            "130": 475.0,
            "138": 480.0,
            "160": 480.0,
            "168": 475.0,
            "176": 475.0,
            "194": 475.0,
            "218": 480.0,
            "32": 475.0,
            "8": 475.0
        },
        "right": {
            "1": 417.8571472167969,
            "144": 500.0,
            "154": 490.0,
            "176": 495.0,
            "194": 485.0,
            "210": 490.0,
            "24": 505.0,
            "30": 490.0,
            "48": 495.0,
            "66": 485.0
        },
        "top": {
            "1": 446.0,
            "128": 535.0,
            "134": 515.0,
            "146": 525.0,
            "152": 537.5,
            "198": 520.0,
            "218": 525.0,
            "22": 520.0,
            "74": 525.0,
            "94": 525.0
        }
    },
    "(1,2,0)": {
        "back": {
            "1": 440.75,
            "158": 525.0,
            "202": 525.0,
            "206": 525.0,
            "30": 525.0,
            "48": 520.0,
            "56": 525.0,
            "70": 515.0,
            "8": 520.0,
            "94": 520.0
        },
        "bottom": {
            "1": 410.0,
            "136": 485.0,
            "138": 482.5,
            "14": 485.0,
            "150": 480.0,
            "176": 485.0,
            "210": 480.0,
            "222": 480.0,
            "6": 480.0,
            "8": 485.0
        },
        "front": {
            "1": 425.0,
            "10": 500.0,
            "134": 505.0,
            "176": 515.0,
            "194": 497.5,
            "26": 497.5,
            "40": 510.0,
            "6": 500.0,
            "82": 495.0,
            "86": 500.0
        },
        "left": {
            "1": 413.125,
            "14": 490.0,
            "18": 480.0,
            "184": 490.0,
            "198": 480.0,
            "202": 480.0,
            "214": 485.0,
            "222": 485.0,
            "48": 480.0,
            "90": 480.0
        },
        "right": {
            "1": 415.76922607421875,
            "14": 490.0,
            "150": 485.0,
            "154": 485.0,
            "160": 480.0,
            "202": 485.0,
            "66": 480.0,
            "74": 490.0,
            "86": 480.0,
            "94": 485.0
        },
        "top": {
            "1": 420.5,
            "138": 510.0,
            "144": 525.0,
            "152": 530.0,
            "176": 525.0,
            "184": 525.0,
            "40": 525.0,
            "78": 515.0,
            "8": 530.0,
            "86": 510.0
        }
    },
    "(1,2,1)": {
        "back": {
            "1": 350.0,
            "130": 450.0,
            "142": 460.0,
            "154": 450.0,
            "160": 485.0,
            "194": 450.0,
            "214": 455.0,
            "26": 450.0,
            "56": 485.0,
            "8": 485.0
        },
        "bottom": {
            "1": 274.28570556640625,
            "130": 335.0,
            "134": 320.0,
            "14": 325.0,
            "150": 320.0,
            "176": 365.0,
            "222": 325.0,
            "66": 340.0,
            "78": 322.5,
            "94": 320.0
        },
        "front": {
            "1": 352.1428527832031,
            "130": 445.0,
            "134": 450.0,
            "136": 485.0,
            "138": 450.0,
            "16": 485.0,
            "194": 445.0,
            "214": 455.0,
            "70": 455.0,
            "82": 445.0
        },
        "left": {
            "1": 375.0,
            "14": 440.0,
            "142": 440.0,
            "160": 492.5,
            "176": 492.5,
            "202": 460.0,
            "218": 462.5,
            "8": 490.0,
            "82": 460.0,
            "90": 465.0
        },
        "right": {
            "1": 384.1666564941406,
            "128": 495.0,
            "136": 500.0,
            "150": 445.0,
            "160": 500.0,
            "168": 500.0,
            "48": 500.0,
            "6": 445.0,
            "66": 465.0,
            "74": 465.0
        },
        "top": {
            "1": 2666.25,
            "144": 1310.0,
            "16": 1305.0,
            "18": 1455.0,
            "184": 1305.0,
            "194": 1465.0,
            "218": 1450.0,
            "48": 1325.0,
            "82": 1455.0,
            "86": 1460.0
        }
    },
    "(1,2,2)": {
        "back": {
            "1": 427.0,
            "128": 515.0,
            "134": 505.0,
            "158": 510.0,
            "18": 495.0,
            "184": 515.0,
            "198": 505.0,
            "26": 507.5,
            "30": 510.0,
            "48": 515.0
        },
        "bottom": {
            "1": 410.0,
            "10": 490.0,
            "144": 490.0,
            "168": 495.0,
            "176": 490.0,
            "206": 490.0,
            "214": 490.0,
            "222": 490.0,
            "32": 495.0,
            "70": 490.0
        },
        "front": {
            "1": 445.0,
            "130": 520.0,
            "150": 520.0,
            "152": 525.0,
            "16": 520.0,
            "198": 520.0,
            "214": 525.0,
            "70": 525.0,
            "82": 520.0,
            "86": 522.5
        },
        "left": {
            "1": 415.0,
            "158": 480.0,
            "160": 485.0,
            "176": 480.0,
            "206": 490.0,
            "214": 475.0,
            "222": 475.0,
            "8": 480.0,
            "86": 475.0,
            "90": 485.0
        },
        "right": {
            "1": 415.0,
            "128": 495.0,
            "136": 495.0,
            "152": 495.0,
            "154": 490.0,
            "202": 490.0,
            "206": 480.0,
            "22": 475.0,
            "32": 485.0,
            "8": 500.0
        },
        "top": {
            "1": 451.3636474609375,
            "138": 530.0,
            "152": 550.0,
            "194": 530.0,
            "198": 525.0,
            "210": 530.0,
            "24": 545.0,
            "30": 530.0,
            "6": 520.0,
            "90": 535.0
        }
    },
    "(2,0,0)": {
        "back": {
            "1": 435.8333435058594,
            "10": 525.0,
            "14": 525.0,
            "154": 525.0,
            "158": 520.0,
            "18": 520.0,
            "218": 520.0,
            "24": 525.0,
            "48": 525.0,
            "94": 525.0
        },
        "bottom": {
            "1": 448.0,
            "130": 525.0,
            "138": 530.0,
            "142": 530.0,
            "146": 525.0,
            "154": 530.0,
            "194": 525.0,
            "32": 525.0,
            "48": 525.0,
            "94": 525.0
        },
        "front": {
            "1": 443.3333435058594,
            "130": 520.0,
            "144": 530.0,
            "146": 520.0,
            "16": 530.0,
            "160": 530.0,
            "202": 525.0,
            "24": 530.0,
            "70": 520.0,
            "8": 525.0
        },
        "left": {
            "1": 412.8571472167969,
            "130": 475.0,
            "14": 475.0,
            "146": 475.0,
            "184": 475.0,
            "206": 475.0,
            "210": 475.0,
            "22": 465.0,
            "40": 482.5,
            "8": 480.0
        },
        "right": {
            "1": 440.0,
            "142": 520.0,
            "206": 520.0,
            "214": 515.0,
            "218": 525.0,
            "32": 520.0,
            "74": 525.0,
            "78": 520.0,
            "90": 525.0,
            "94": 520.0
        },
        "top": {
            "1": 430.0,
            "134": 510.0,
            "14": 510.0,
            "176": 515.0,
            "194": 510.0,
            "210": 510.0,
            "214": 510.0,
            "32": 510.0,
            "8": 515.0,
            "90": 515.0
        }
    },
    "(2,0,1)": {
        "back": {
            "1": 348.3333435058594,
            "154": 450.0,
            "158": 442.5,
            "202": 450.0,
            "24": 455.0,
            "32": 456.6666564941406,
            "40": 455.0,
            "6": 435.0,
            "8": 460.0,
            "82": 445.0
        },
        "bottom": {
            "1": 316.1111145019531,
            "128": 450.0,
            "150": 420.0,
            "194": 420.0,
            "214": 425.0,
            "24": 450.0,
            "56": 450.0,
            "78": 427.5,
            "8": 450.0,
            "86": 425.0
        },
        "front": {
            "1": 344.375,
            "150": 435.0,
            "154": 445.0,
            "168": 455.0,
            "184": 455.0,
            "206": 440.0,
            "210": 445.0,
            "222": 445.0,
            "30": 440.0,
            "82": 440.0
        },
        "left": {
            "1": 280.0,
            "16": 360.0,
            "176": 355.0,
            "206": 295.0,
            "218": 330.0,
            "222": 295.0,
            "26": 330.0,
            "48": 355.0,
            "78": 295.0,
            "82": 330.0
        },
        "right": {
            "1": 345.0,
            "14": 440.0,
            "142": 445.0,
            "154": 455.0,
            "168": 485.0,
            "184": 485.0,
            "202": 460.0,
            "222": 445.0,
            "8": 485.0,
            "94": 440.0
        },
        "top": {
            "1": 328.0,
            "210": 440.0,
            "218": 440.0,
            "222": 440.0,
            "24": 460.0,
            "26": 440.0,
            "30": 440.0,
            "48": 455.0,
            "8": 460.0,
            "82": 435.0
        }
    },
    "(2,0,2)": {
        "back": {
            "1": 425.0,
            "136": 520.0,
            "138": 515.0,
            "150": 515.0,
            "160": 520.0,
            "214": 515.0,
            "222": 520.0,
            "24": 520.0,
            "26": 520.0,
            "6": 510.0
        },
        "bottom": {
            "1": 443.6363525390625,
            "136": 525.0,
            "14": 530.0,
            "160": 525.0,
            "176": 525.0,
            "194": 525.0,
            "6": 525.0,
            "66": 525.0,
            "78": 525.0,
            "86": 520.0
        },
        "front": {
            "1": 440.0,
            "142": 520.0,
            "160": 525.0,
            "176": 530.0,
            "202": 525.0,
            "206": 520.0,
            "22": 520.0,
            "222": 525.0,
            "40": 530.0,
            "6": 515.0
        },
        "left": {
            "1": 410.0,
            "10": 475.0,
            "142": 475.0,
            "154": 475.0,
            "184": 460.0,
            "218": 470.0,
            "22": 470.0,
            "24": 470.0,
            "30": 475.0,
            "56": 467.5
        },
        "right": {
            "1": 440.0,
            "10": 527.5,
            "136": 525.0,
            "146": 520.0,
            "158": 525.0,
            "160": 520.0,
            "22": 515.0,
            "222": 525.0,
            "66": 525.0,
            "8": 525.0
        },
        "top": {
            "1": 436.81817626953125,
            "128": 515.0,
            "136": 515.0,
            "150": 500.0,
            "158": 510.0,
            "168": 515.0,
            "210": 510.0,
            "22": 500.0,
            "24": 515.0,
            "48": 515.0
        }
    },
    "(2,1,0)": {
        "back": {
            "1": 430.0,
            "128": 520.0,
            "154": 515.0,
            "16": 515.0,
            "206": 515.0,
            "218": 515.0,
            "26": 510.0,
            "70": 510.0,
            "86": 510.0,
            "94": 520.0
        },
        "bottom": {
            "1": 423.5294189453125,
            "134": 495.0,
            "146": 495.0,
            "154": 500.0,
            "176": 490.0,
            "218": 495.0,
            "48": 490.0,
            "56": 495.0,
            "74": 490.0,
            "94": 500.0
        },
        "front": {
            "1": 431.6666564941406,
            "14": 520.0,
            "144": 525.0,
            "146": 515.0,
            "150": 515.0,
            "22": 515.0,
            "32": 525.0,
            "56": 525.0,
            "70": 515.0,
            "74": 520.0
        },
        "left": {
            "1": 410.0,
            "154": 475.0,
            "160": 480.0,
            "168": 480.0,
            "194": 465.0,
            "206": 470.0,
            "210": 470.0,
            "22": 465.0,
            "48": 475.0,
            "90": 475.0
        },
        "right": {
            "1": 434.6428527832031,
            "144": 515.0,
            "146": 515.0,
            "16": 515.0,
            "18": 510.0,
            "22": 510.0,
            "56": 515.0,
            "78": 515.0,
            "90": 510.0,
            "94": 515.0
        },
        "top": {
            "1": 425.8333435058594,
            "136": 510.0,
            "158": 510.0,
            "16": 510.0,
            "198": 505.0,
            "210": 505.0,
            "70": 505.0,
            "74": 507.5,
            "8": 505.0,
            "82": 500.0
        }
    },
    "(2,1,1)": {
        "back": {
            "1": 363.3333435058594,
            "146": 465.0,
            "154": 470.0,
            "24": 475.0,
            "26": 470.0,
            "32": 477.5,
            "56": 475.0,
            "74": 470.0,
            "8": 475.0,
            "82": 470.0
        },
        "bottom": {
            "1": 327.8571472167969,
            "10": 435.0,
            "128": 450.0,
            "130": 425.0,
            "142": 437.5,
            "146": 425.0,
            "158": 435.0,
            "176": 450.0,
            "210": 430.0,
            "86": 435.0
        },
        "front": {
            "1": 360.4166564941406,
            "14": 470.0,
            "144": 470.0,
            "18": 465.0,
            "194": 465.0,
            "206": 470.0,
            "26": 465.0,
            "40": 475.0,
            "66": 465.0,
            "70": 465.0
        },
        "left": {
            "1": 308.75,
            "136": 395.0,
            "142": 330.0,
            "154": 370.0,
            "18": 370.0,
            "198": 330.0,
            "214": 325.0,
            "222": 330.0,
            "66": 365.0,
            "70": 330.0
        },
        "right": {
            "1": 510.0,
            "128": 580.0,
            "14": 565.0,
            "142": 565.0,
            "144": 580.0,
            "146": 565.0,
            "154": 575.0,
            "160": 575.0,
            "168": 575.0,
            "82": 565.0
        },
        "top": {
            "1": 335.0,
            "10": 450.0,
            "130": 445.0,
            "136": 475.0,
            "154": 455.0,
            "206": 455.0,
            "32": 475.0,
            "48": 470.0,
            "66": 450.0,
            "8": 465.0
        }
    },
    "(2,1,2)": {
        "back": {
            "1": 447.1428527832031,
            "158": 540.0,
            "16": 545.0,
            "168": 545.0,
            "194": 535.0,
            "198": 535.0,
            "206": 540.0,
            "24": 545.0,
            "48": 545.0,
            "94": 535.0
        },
        "bottom": {
            "1": 425.0,
            "128": 507.5,
            "134": 500.0,
            "136": 510.0,
            "14": 505.0,
            "146": 505.0,
            "214": 505.0,
            "30": 505.0,
            "32": 510.0,
            "6": 505.0
        },
        "front": {
            "1": 440.71429443359375,
            "128": 525.0,
            "130": 515.0,
            "134": 520.0,
            "138": 515.0,
            "158": 525.0,
            "16": 522.5,
            "176": 515.0,
            "218": 525.0,
            "66": 520.0
        },
        "left": {
            "1": 410.71429443359375,
            "136": 460.0,
            "138": 460.0,
            "154": 475.0,
            "16": 450.0,
            "176": 465.0,
            "184": 465.0,
            "48": 465.0,
            "66": 460.0,
            "94": 450.0
        },
        "right": {
            "1": 442.5,
            "128": 525.0,
            "130": 522.5,
            "150": 525.0,
            "194": 525.0,
            "206": 530.0,
            "22": 525.0,
            "70": 530.0,
            "74": 525.0,
            "78": 535.0
        },
        "top": {
            "1": 454.5454406738281,
            "130": 525.0,
            "134": 525.0,
            "138": 530.0,
            "168": 540.0,
            "198": 525.0,
            "206": 530.0,
            "26": 530.0,
            "8": 540.0,
            "94": 525.0
        }
    },
    "(2,2,0)": {
        "back": {
            "1": 448.3333435058594,
            "130": 520.0,
            "146": 520.0,
            "152": 525.0,
            "214": 525.0,
            "218": 525.0,
            "6": 525.0,
            "70": 525.0,
            "82": 525.0,
            "94": 525.0
        },
        "bottom": {
            "1": 420.8333435058594,
            "128": 490.0,
            "144": 485.0,
            "16": 490.0,
            "218": 490.0,
            "222": 495.0,
            "30": 495.0,
            "48": 490.0,
            "56": 486.6666564941406,
            "94": 495.0
        },
        "front": {
            "1": 435.0,
            "154": 505.0,
            "16": 520.0,
            "198": 505.0,
            "206": 510.0,
            "222": 510.0,
            "30": 510.0,
            "32": 520.0,
            "78": 505.0,
            "90": 505.0
        },
        "left": {
            "1": 411.25,
            "150": 460.0,
            "154": 470.0,
            "16": 470.0,
            "194": 470.0,
            "198": 465.0,
            "206": 465.0,
            "40": 475.0,
            "48": 470.0,
            "8": 470.0
        },
        "right": {
            "1": 431.0,
            "134": 510.0,
            "146": 510.0,
            "160": 510.0,
            "176": 505.0,
            "194": 510.0,
            "198": 510.0,
            "210": 505.0,
            "218": 510.0,
            "82": 510.0
        },
        "top": {
            "1": 447.77777099609375,
            "128": 550.0,
            "136": 550.0,
            "176": 548.3333129882813,
            "206": 530.0,
            "32": 555.0,
            "56": 555.0,
            "6": 520.0,
            "70": 535.0,
            "74": 530.0
        }
    },
    "(2,2,1)": {
        "back": {
            "1": 436.4285583496094,
            "142": 510.0,
            "150": 505.0,
            "160": 510.0,
            "168": 505.0,
            "18": 500.0,
            "194": 510.0,
            "210": 510.0,
            "222": 510.0,
            "74": 515.0
        },
        "bottom": {
            "1": 328.125,
            "142": 410.0,
            "144": 440.0,
            "184": 440.0,
            "30": 410.0,
            "56": 440.0,
            "66": 425.0,
            "70": 410.0,
            "74": 430.0,
            "78": 410.0
        },
        "front": {
            "1": 433.75,
            "160": 505.0,
            "18": 505.0,
            "198": 505.0,
            "214": 505.0,
            "26": 510.0,
            "56": 510.0,
            "6": 505.0,
            "74": 510.0,
            "78": 507.5
        },
        "left": {
            "1": 395.5555419921875,
            "10": 490.0,
            "14": 490.0,
            "150": 485.0,
            "158": 490.0,
            "18": 480.0,
            "194": 485.0,
            "210": 485.0,
            "26": 485.0,
            "30": 495.0
        },
        "right": {
            "1": 438.3333435058594,
            "134": 515.0,
            "138": 520.0,
            "142": 525.0,
            "150": 525.0,
            "152": 515.0,
            "198": 520.0,
            "210": 515.0,
            "66": 520.0,
            "90": 525.0
        },
        "top": {
            "1": 422.5,
            "136": 515.0,
            "138": 512.5,
            "14": 500.0,
            "142": 500.0,
            "16": 520.0,
            "202": 515.0,
            "26": 515.0,
            "6": 495.0,
            "90": 515.0
        }
    },
    "(2,2,2)": {
        "back": {
            "1": 427.5,
            "14": 505.0,
            "150": 500.0,
            "168": 515.0,
            "194": 500.0,
            "22": 500.0,
            "222": 505.0,
            "30": 510.0,
            "6": 500.0,
            "8": 520.0
        },
        "bottom": {
            "1": 422.22222900390625,
            "134": 490.0,
            "14": 500.0,
            "160": 505.0,
            "176": 500.0,
            "206": 500.0,
            "22": 490.0,
            "222": 497.5,
            "66": 495.0,
            "70": 490.0
        },
        "front": {
            "1": 450.71429443359375,
            "146": 520.0,
            "152": 530.0,
            "158": 530.0,
            "16": 525.0,
            "194": 530.0,
            "198": 525.0,
            "24": 525.0,
            "56": 525.0,
            "74": 530.0
        },
        "left": {
            "1": 409.5833435058594,
            "134": 465.0,
            "160": 460.0,
            "168": 463.3333435058594,
            "206": 470.0,
            "210": 465.0,
            "66": 465.0,
            "78": 470.0,
            "8": 470.0,
            "86": 465.0
        },
        "right": {
            "1": 439.0,
            "134": 520.0,
            "138": 520.0,
            "146": 515.0,
            "150": 510.0,
            "152": 515.0,
            "218": 520.0,
            "26": 520.0,
            "32": 507.5,
            "78": 520.0
        },
        "top": {
            "1": 460.0,
            "130": 530.0,
            "138": 535.0,
            "14": 540.0,
            "16": 550.0,
            "18": 530.0,
            "202": 540.0,
            "222": 540.0,
            "40": 550.0,
            "78": 540.0
        }
    },
    "Grid Dimensions (x,y,z)": [
        3.0,
        3.0,
        3.0
    ]
}